hdface/__init__.py
hdface/hdface.py
hdface/image_tools.py
hdface/models.py
hdface/utils.py
hdface/data/lnet.data
hdface/data/onet.data
hdface/data/pnet.data
hdface/data/rnet.data
hdface-0.1.3.dist-info/LICENSE
hdface-0.1.3.dist-info/METADATA
hdface-0.1.3.dist-info/WHEEL
hdface-0.1.3.dist-info/top_level.txt
hdface-0.1.3.dist-info/RECORD
